jionlp/__init__.py
jionlp/algorithm/__init__.py
jionlp/algorithm/cws/__init__.py
jionlp/algorithm/cws/cws_data_converter.py
jionlp/algorithm/keyphrase/__init__.py
jionlp/algorithm/keyphrase/extract_keyphrase.py
jionlp/algorithm/keyphrase/pos_combine_weights.json
jionlp/algorithm/ner/__init__.py
jionlp/algorithm/ner/analyse_dataset.py
jionlp/algorithm/ner/lexicon_ner.py
jionlp/algorithm/ner/money_extractor.py
jionlp/algorithm/ner/ner_accelerate.py
jionlp/algorithm/ner/ner_data_converter.py
jionlp/algorithm/ner/ner_entity_compare.py
jionlp/algorithm/ner/time_extractor.py
jionlp/algorithm/sentiment/__init__.py
jionlp/algorithm/sentiment/sentiment_analysis.py
jionlp/algorithm/simhash/__init__.py
jionlp/algorithm/simhash/api.py
jionlp/algorithm/simhash/simhash.py
jionlp/algorithm/simhash/simhash_redis.py
jionlp/algorithm/summary/__init__.py
jionlp/algorithm/summary/extract_summary.py
jionlp/algorithm/text_classification/__init__.py
jionlp/algorithm/text_classification/analyse_dataset.py
jionlp/algorithm/text_classification/analyse_freq_words.py
jionlp/dictionary/TODO.txt
jionlp/dictionary/__init__.py
jionlp/dictionary/advertisement.txt
jionlp/dictionary/char_distribution.zip
jionlp/dictionary/china_location.zip
jionlp/dictionary/china_location_change.txt
jionlp/dictionary/chinese_char_dictionary.zip
jionlp/dictionary/chinese_idiom.zip
jionlp/dictionary/chinese_word_dictionary.zip
jionlp/dictionary/description.txt
jionlp/dictionary/dictionary_loader.py
jionlp/dictionary/idf.zip
jionlp/dictionary/landline_phone_area_code.txt
jionlp/dictionary/negative_words.txt
jionlp/dictionary/phone_location.zip
jionlp/dictionary/pinyin_phrase.zip
jionlp/dictionary/politics.txt
jionlp/dictionary/pornography.zip
jionlp/dictionary/qita.txt
jionlp/dictionary/sentiment_expand_words.txt
jionlp/dictionary/sentiment_words.zip
jionlp/dictionary/sim2tra_char.txt
jionlp/dictionary/sim2tra_word.txt
jionlp/dictionary/stopwords.txt
jionlp/dictionary/telecom_operator.txt
jionlp_py39-1.3.45.dist-info/LICENSE
jionlp_py39-1.3.45.dist-info/METADATA
jionlp_py39-1.3.45.dist-info/WHEEL
jionlp_py39-1.3.45.dist-info/entry_points.txt
jionlp_py39-1.3.45.dist-info/top_level.txt
jionlp_py39-1.3.45.dist-info/RECORD
