Metadata-Version: 2.1
Name: jionlp-py39
Version: 1.3.45
Summary: Chinese NLPreprocessing & Parsing
Home-page: https://github.com/dongrixinyu/JioNLP
Author: dongrixinyu
Author-email: dongrixinyu.89@163.com
License: Apache License 2.0
Platform: UNKNOWN
License-File: LICENSE
Requires-Dist: numpy
Requires-Dist: jieba
Requires-Dist: requests
Requires-Dist: zipfile36
Requires-Dist: spacy-pkuseg
